geedar_lib/__init__.py
geedar_lib/geedar.py
geedar_lib/utils.py
geedar_lib-0.1.0.dist-info/LICENSE
geedar_lib-0.1.0.dist-info/METADATA
geedar_lib-0.1.0.dist-info/WHEEL
geedar_lib-0.1.0.dist-info/RECORD
