Metadata-Version: 2.1
Name: geedar-lib
Version: 0.1.0
Summary: 
Author: lucasuchoa98
Author-email: lucasuchoalg@gmail.com
Requires-Python: >=3.9,<4.0
Classifier: Development Status :: 2 - Pre-Alpha
Classifier: Intended Audience :: Developers
Classifier: Natural Language :: Portuguese (Brazilian)
Classifier: Programming Language :: Python :: 3
Classifier: Programming Language :: Python :: 3.9
Classifier: Programming Language :: Python :: 3.10
Classifier: Programming Language :: Python :: 3.11
Classifier: Programming Language :: Python :: 3.11
Classifier: Topic :: Education
Requires-Dist: earthengine-api (>=0.1.348,<0.2.0)
Requires-Dist: fastkml (>=0.12,<0.13)
Requires-Dist: pandas (>=2.0.0,<3.0.0)
Project-URL: Bug Tracker, https://github.com/lucasuchoa98/geedar-lib/issues
Project-URL: Código, https://github.com/lucasuchoa98/geedar-lib
Project-URL: Documentação, https://geedar-lib.readthedocs.io/en/latest/
